{"type": "Feature", "id": 12517972, "geometry": {"type": "Point", "coordinates": [54.199799, 39.6716]}, "properties": {"woe:id": 12517972, "woe:parent_id": 1936535, "woe:name": "Dzhebel Airport", "woe:placetype": 14, "woe:placetype_name": "Airport", "woe:lang": "ENG", "iso:country": "TM", "meta:provider": ["geoplanet:7.3.1", "geoplanet:7.3.2", "geoplanet:7.4.0", "geoplanet:7.4.1", "geoplanet:7.5.1", "geoplanet:7.5.2", "geoplanet:7.6.0", "geoplanet:7.8.1", "geoplanet:7.9.0", "geoplanet:7.10.0", "geoplanet:8.0.0", "woeplanet:8.0.0"], "meta:indexed": "2020-08-20T20:57:42.913961", "meta:updated": "2020-10-14T11:18:04.968156", "woe:hierarchy": {"continent": 24865671, "country": 23424972, "town": 0, "planet": 1, "county": 0, "suburb": 0, "state": 2347349, "region": 0, "localadmin": 0}, "woe:timezone_id": 28350810, "woe:hash": "tpn99mgpff5r", "woe:centroid": [54.199799, 39.6716], "geom:latitude": 39.6716, "geom:longitude": 54.199799, "geom:hash": "tpn99mgpff5r", "woe:latitude": 39.6716, "geom:centroid": [54.199799, 39.6716], "woe:longitude": 54.199799, "woe:repo": "woeplanet-airport-tm", "geom:area": 0.0, "woe:scale": 19}}