{"type": "Feature", "id": 12517966, "geometry": {"type": "Point", "coordinates": [57.2262, 41.2103]}, "properties": {"woe:id": 12517966, "woe:parent_id": 1936545, "woe:name": "Charyshly 2 Airport", "woe:placetype": 14, "woe:placetype_name": "Airport", "woe:lang": "ENG", "iso:country": "TM", "meta:provider": ["geoplanet:7.3.1", "geoplanet:7.3.2", "geoplanet:7.4.0", "geoplanet:7.4.1", "geoplanet:7.5.1", "geoplanet:7.5.2", "geoplanet:7.6.0", "geoplanet:7.8.1", "geoplanet:7.9.0", "geoplanet:7.10.0", "geoplanet:8.0.0", "woeplanet:8.0.0"], "meta:indexed": "2020-08-20T20:57:42.909047", "meta:updated": "2020-10-14T11:18:04.969752", "woe:hierarchy": {"continent": 24865671, "country": 23424972, "town": 0, "planet": 1, "county": 0, "suburb": 0, "state": 2347351, "region": 0, "localadmin": 0}, "woe:timezone_id": 28350810, "woe:hash": "tr2dqnng7heq", "woe:centroid": [57.2262, 41.2103], "geom:latitude": 41.2103, "geom:longitude": 57.2262, "geom:hash": "tr2dqnng7heq", "woe:latitude": 41.2103, "geom:centroid": [57.2262, 41.2103], "woe:longitude": 57.2262, "woe:repo": "woeplanet-airport-tm", "geom:area": 0.0, "woe:scale": 19}}