{"type": "Feature", "id": 12517987, "properties": {"woe:id": 12517987, "woe:parent_id": 1936318, "woe:name": "Khauz-Khan North Airport", "woe:placetype": 14, "woe:placetype_name": "Airport", "woe:lang": "ENG", "iso:country": "TM", "meta:provider": ["geoplanet:7.3.1", "geoplanet:7.3.2", "geoplanet:7.4.0", "geoplanet:7.4.1", "geoplanet:7.5.1", "geoplanet:7.5.2", "geoplanet:7.6.0", "geoplanet:7.8.1", "geoplanet:7.9.0", "geoplanet:7.10.0", "geoplanet:8.0.0", "woeplanet:8.0.0"], "meta:indexed": "2020-08-20T20:57:42.926193", "meta:updated": "2020-08-22T01:58:53.760185", "woe:hierarchy": {"continent": 24865671, "country": 23424972, "town": 0, "planet": 1, "county": 0, "suburb": 0, "state": 2347350, "region": 0, "localadmin": 0}, "woe:timezone_id": 28350810, "woe:hash": "tqesv56d5zf6", "woe:centroid": [61.395199, 37.415699], "geom:latitude": 37.415699, "geom:longitude": 61.395199, "geom:hash": "tqesv56d5zf6", "woe:latitude": 37.415699, "geom:centroid": [61.395199, 37.415699], "woe:longitude": 61.395199, "woe:repo": "woeplanet-airport-tm"}, "geometry": {"coordinates": [61.395199, 37.415699], "type": "Point"}}